[
  {
    "name": "Migombani Cottage",
    "start": "2020-08-03T08:00+0300",
    "end": "2020-08-04T08:00+0300",
    "latitude": null,
    "latitude": null

  },
  {
    "name": "Tortilis Ngorongoro",
    "start": "2020-08-04T08:01+0300",
    "end": "2020-08-05T08:00+0300",
    "latitude": null,
    "latitude": null

  },
  {
    "name": "Thorn Tree Camp",
    "start": "2020-08-05T08:01+0300",
    "end": "2020-08-06T08:00+0300",
    "latitude": null,
    "latitude": null

  },
  {
    "name": "Thorn Tree Camp",
    "start": "2020-08-06T08:01+0300",
    "end": "2020-08-07T08:00+0300",
    "latitude": null,
    "latitude": null

  },
  {
    "name": "Tarangire View Camp",
    "start": "2020-08-07T08:01+0300",
    "end": "2020-08-08T08:00+0300",
    "latitude": null,
    "latitude": null

  }
]